{
  "caption":[
    {"id":"1",
      "ifcos":{
        "title":"【6月签到卡】猫耳总裁请查收！",
        "time":"2018/5/30",
        "content":"6月将至，</br>新的签到卡也要到来了！</br>这次的全新签到卡，</br>是带着猫耳发箍的李泽言哦~</br>以儿童节为开端的6月，</br>希望大家都能永葆一份可贵的童心</br>在未来的每一天</br>都开心快乐！",
        "introduce":"2018年6月签到羁绊 【李泽言·稚气可贵】",
        "detailsOne":"../images/newpaper/sixlzy1.png",
        "detailsTwo":"../images/newpaper/sixlzy2.png",
        "way":["【获取方式】</br>1.2018年6月期间，累计签到达到28天，即可获得【李泽言·稚气可贵】签到羁绊；</br>2.此羁绊目前只有累计签到领取这一种获取途径，暂无其他获取方式。","</br>【羁绊信息】</br>1.获得羁绊 可获得女主的朋友圈 形迹可疑</br>.羁绊进化 可获得李泽言的朋友圈 天天过节"]
      }
    },
    {"id":"2",
      "ifcos":{
        "title":"【5月签到卡】繁花5月，怎及你",
        "time":"2018/05/03",
        "content":"假期快乐~</br>终于迎来了难得的假日，</br>你们都是如何度过的呢？</br>小编我啊，</br>正抱着电脑窝在床上。</br>天气很好，窗户半开</br>窗前不知名的花开了一树，</br>是即将到来的夏天啊。</br>游戏内也将迎来5月签到羁绊，</br>本月是属于洛洛的~</br>今天的阳光还有他的微笑</br>都有夏天的味道。",
        "introduce":"2018年5月签到羁绊 【周棋洛·夏日香气】",
        "detailsOne":"../images/newpaper/fivezlq1.jpg",
        "detailsTwo":"../images/newpaper/fivezlq2.jpg",
        "way":["【获取方式】</br>1.2018年5月期间，累计签到达到28天，即可获得【周棋洛·夏日香气】签到羁绊；</br>2.此羁绊目前只有累计签到领取这一种获取途径，暂无其他获取方式。","</br>【羁绊信息】</br>1.获得羁绊 可获得周棋洛的朋友圈 pose指导</br>2.羁绊进化 可获得周棋洛的朋友圈 付费订阅"]
      }
    },
    {"id":"3",
      "ifcos":{
        "title":"【5月签到卡】繁花5月，怎及你",
        "time":"2018/05/30",
        "content":"假期快乐~</br>终于迎来了难得的假日，</br>你们都是如何度过的呢？</br>小编我啊，</br>正抱着电脑窝在床上。</br>天气很好，窗户半开</br>窗前不知名的花开了一树，</br>是即将到来的夏天啊。</br>游戏内也将迎来5月签到羁绊，</br>本月是属于洛洛的~</br>今天的阳光还有他的微笑</br>都有夏天的味道。",
        "introduce":"2018年5月签到羁绊 【周棋洛·夏日香气】",
        "detailsOne":"../images/newpaper/fivezlq1.jpg",
        "detailsTwo":"../images/newpaper/fivezlq2.jpg",
        "way":["【获取方式】</br>1.2018年5月期间，累计签到达到28天，即可获得【周棋洛·夏日香气】签到羁绊；</br>2.此羁绊目前只有累计签到领取这一种获取途径，暂无其他获取方式。","</br>【羁绊信息】</br>1.获得羁绊 可获得周棋洛的朋友圈 pose指导</br>2.羁绊进化 可获得周棋洛的朋友圈 付费订阅"]
      }
    },
    {"id":"3",
      "ifcos":{
        "title":"【5月签到卡】繁花5月，怎及你",
        "time":"2018/05/30",
        "content":"假期快乐~</br>终于迎来了难得的假日，</br>你们都是如何度过的呢？</br>小编我啊，</br>正抱着电脑窝在床上。</br>天气很好，窗户半开</br>窗前不知名的花开了一树，</br>是即将到来的夏天啊。</br>游戏内也将迎来5月签到羁绊，</br>本月是属于洛洛的~</br>今天的阳光还有他的微笑</br>都有夏天的味道。",
        "introduce":"2018年5月签到羁绊 【周棋洛·夏日香气】",
        "detailsOne":"../images/newpaper/fivezlq1.jpg",
        "detailsTwo":"../images/newpaper/fivezlq2.jpg",
        "way":["【获取方式】</br>1.2018年5月期间，累计签到达到28天，即可获得【周棋洛·夏日香气】签到羁绊；</br>2.此羁绊目前只有累计签到领取这一种获取途径，暂无其他获取方式。","</br>【羁绊信息】</br>1.获得羁绊 可获得周棋洛的朋友圈 pose指导</br>2.羁绊进化 可获得周棋洛的朋友圈 付费订阅"]
      }
    },
    {"id":"3",
      "ifcos":{
        "title":"【5月签到卡】繁花5月，怎及你",
        "time":"2018/05/30",
        "content":"假期快乐~</br>终于迎来了难得的假日，</br>你们都是如何度过的呢？</br>小编我啊，</br>正抱着电脑窝在床上。</br>天气很好，窗户半开</br>窗前不知名的花开了一树，</br>是即将到来的夏天啊。</br>游戏内也将迎来5月签到羁绊，</br>本月是属于洛洛的~</br>今天的阳光还有他的微笑</br>都有夏天的味道。",
        "introduce":"2018年5月签到羁绊 【周棋洛·夏日香气】",
        "detailsOne":"../images/newpaper/fivezlq1.jpg",
        "detailsTwo":"../images/newpaper/fivezlq2.jpg",
        "way":["【获取方式】</br>1.2018年5月期间，累计签到达到28天，即可获得【周棋洛·夏日香气】签到羁绊；</br>2.此羁绊目前只有累计签到领取这一种获取途径，暂无其他获取方式。","</br>【羁绊信息】</br>1.获得羁绊 可获得周棋洛的朋友圈 pose指导</br>2.羁绊进化 可获得周棋洛的朋友圈 付费订阅"]
      }
    },
    {"id":"1",
      "ifcos":{
        "title":"【6月签到卡】猫耳总裁请查收！",
        "time":"2018/5/30",
        "content":"6月将至，</br>新的签到卡也要到来了！</br>这次的全新签到卡，</br>是带着猫耳发箍的李泽言哦~</br>以儿童节为开端的6月，</br>希望大家都能永葆一份可贵的童心</br>在未来的每一天</br>都开心快乐！",
        "introduce":"2018年6月签到羁绊 【李泽言·稚气可贵】",
        "detailsOne":"../images/newpaper/sixlzy1.png",
        "detailsTwo":"../images/newpaper/sixlzy2.png",
        "way":["【获取方式】</br>1.2018年6月期间，累计签到达到28天，即可获得【李泽言·稚气可贵】签到羁绊；</br>2.此羁绊目前只有累计签到领取这一种获取途径，暂无其他获取方式。","</br>【羁绊信息】</br>1.获得羁绊 可获得女主的朋友圈 形迹可疑</br>.羁绊进化 可获得李泽言的朋友圈 天天过节"]
      }
    },
    {"id":"1",
      "ifcos":{
        "title":"【6月签到卡】猫耳总裁请查收！",
        "time":"2018/5/30",
        "content":"6月将至，</br>新的签到卡也要到来了！</br>这次的全新签到卡，</br>是带着猫耳发箍的李泽言哦~</br>以儿童节为开端的6月，</br>希望大家都能永葆一份可贵的童心</br>在未来的每一天</br>都开心快乐！",
        "introduce":"2018年6月签到羁绊 【李泽言·稚气可贵】",
        "detailsOne":"../images/newpaper/sixlzy1.png",
        "detailsTwo":"../images/newpaper/sixlzy2.png",
        "way":["【获取方式】</br>1.2018年6月期间，累计签到达到28天，即可获得【李泽言·稚气可贵】签到羁绊；</br>2.此羁绊目前只有累计签到领取这一种获取途径，暂无其他获取方式。","</br>【羁绊信息】</br>1.获得羁绊 可获得女主的朋友圈 形迹可疑</br>.羁绊进化 可获得李泽言的朋友圈 天天过节"]
      }
    }
  ]
}